datatables_ajax/__init__.py
datatables_ajax/datatables.py
django_datatables_ajax-0.8.dist-info/LICENSE
django_datatables_ajax-0.8.dist-info/METADATA
django_datatables_ajax-0.8.dist-info/WHEEL
django_datatables_ajax-0.8.dist-info/top_level.txt
django_datatables_ajax-0.8.dist-info/RECORD
