Metadata-Version: 2.1
Name: django-datatables-ajax
Version: 0.8
Summary: Lightweight Django class for a full Datatables server processing implementation
Home-page: https://github.com/peppelinux/django-datatables-ajax
Author: Giuseppe De Marco
Author-email: giuseppe.demarco@unical.it
License: BSD
Platform: UNKNOWN
Classifier: Development Status :: 5 - Production/Stable
Classifier: License :: OSI Approved :: BSD License
Classifier: Programming Language :: Python :: 3 :: Only
Classifier: Operating System :: POSIX :: Linux
Requires-Dist: django
